exodata/__init__.py
exodata/assumptions.py
exodata/astroclasses.py
exodata/astroquantities.py
exodata/database.py
exodata/equations.py
exodata/example.py
exodata/flags.py
exodata/params.py
exodata/plots.py
exodata/data/magnitude_conversion.dat
exodata/data/magnitude_estimation.dat
exodata/data/quadratic.dat
exodata-1.1.1.dist-info/DESCRIPTION.rst
exodata-1.1.1.dist-info/METADATA
exodata-1.1.1.dist-info/metadata.json
exodata-1.1.1.dist-info/pbr.json
exodata-1.1.1.dist-info/RECORD
exodata-1.1.1.dist-info/top_level.txt
exodata-1.1.1.dist-info/WHEEL
