Metadata-Version: 2.0
Name: exodata
Version: 1.1.1
Summary: Exoplanet catalogue interface
Home-page: https://github.com/ryanvarley/exodata
Author: Ryan Varley
Author-email: oecpy@ryanvarley.uk
License: GPLv3
Platform: UNKNOWN
Classifier: Development Status :: 4 - Beta
Classifier: Intended Audience :: Science/Research
Classifier: Topic :: Scientific/Engineering :: Astronomy
Classifier: License :: OSI Approved :: GNU General Public License v3 (GPLv3)
Classifier: Programming Language :: Python :: 3.4
Classifier: Programming Language :: Python :: 3.3
Classifier: Programming Language :: Python :: 3
Classifier: Programming Language :: Python :: 2.7
Classifier: Programming Language :: Python :: 2.6
Requires-Dist: numpy
Requires-Dist: quantities
Requires-Dist: nose (>=1.0)
Requires-Dist: matplotlib (>=1.3.1)
Requires-Dist: requests
